dayabay_model_official/__init__.py
dayabay_model_official/model_dayabay.py
dayabay_model_official/model_dayabay.yaml
dayabay_model_official/bundles/refine_detector_data.py
dayabay_model_official/bundles/refine_lsnl_data.py
dayabay_model_official/bundles/refine_neutrino_rate_data.py
dayabay_model_official/bundles/sync_neutrino_rate_detector_data.py
dayabay_model_official/bundles/sync_reactor_detector_data.py
dayabay_model_official/tools/__init__.py
dayabay_model_official/tools/validate_dataset.py
dayabay_model_official/tools/validate_load_array.py
dayabay_model_official-1.4.1.dist-info/licenses/LICENSE
dayabay_model_official-1.4.1.dist-info/METADATA
dayabay_model_official-1.4.1.dist-info/WHEEL
dayabay_model_official-1.4.1.dist-info/top_level.txt
dayabay_model_official-1.4.1.dist-info/RECORD
