Metadata-Version: 2.4
Name: dayabay-model-official
Version: 1.4.1
Summary: Official model of the Daya Bay reactor antineutrino experiment for neutrino oscillation analysis based on gadolinium capture data.
Author-email: Daya Bay Collaboration <dagflow@jinr.ru>
Maintainer-email: DAGModelling Team <dagflow@jinr.ru>
License-Expression: MIT
Project-URL: Bug Tracker, https://github.com/dagflow-team/dayabay-model-official/issues
Project-URL: DAGModelling Team, https://github.com/dagflow-team
Project-URL: documentation, https://github.com/dagflow-team/dayabay-model-official/wiki
Project-URL: homepage, https://github.com/dagflow-team/dayabay-model-official
Project-URL: repository, https://github.com/dagflow-team/dayabay-model-official
Classifier: Programming Language :: Python :: 3 :: Only
Classifier: Programming Language :: Python :: 3.11
Classifier: Programming Language :: Python :: 3.12
Classifier: Programming Language :: Python :: 3.13
Requires-Python: >=3.11
License-File: LICENSE
Requires-Dist: colorama
Requires-Dist: dgm-fit>=0.2
Requires-Dist: dgm-reactor-neutrino>=0.2.2
Requires-Dist: more-itertools
Requires-Dist: semver
Provides-Extra: test
Requires-Dist: dgm-reactor-neutrino[test]>=0.2.2; extra == "test"
Requires-Dist: ipykernel; extra == "test"
Requires-Dist: ipython; extra == "test"
Requires-Dist: ipywidgets; extra == "test"
Requires-Dist: nbconvert; extra == "test"
Requires-Dist: parameterized; extra == "test"
Requires-Dist: pygraphviz; extra == "test"
Dynamic: license-file
